README.txt
setup.py
JYAliYun/AliYunAccount.py
JYAliYun/AliYunObject.py
JYAliYun/__init__.py
JYAliYun.egg-info/PKG-INFO
JYAliYun.egg-info/SOURCES.txt
JYAliYun.egg-info/dependency_links.txt
JYAliYun.egg-info/entry_points.txt
JYAliYun.egg-info/requires.txt
JYAliYun.egg-info/top_level.txt
JYAliYun/AliYunMNS/AliMNSObject.py
JYAliYun/AliYunMNS/AliMNSServer.py
JYAliYun/AliYunMNS/AliMNSTopics.py
JYAliYun/AliYunMNS/__init__.py
JYAliYun/AliYunMNS/cli.py
JYAliYun/AliYunOSS/__init__.py
JYAliYun/AliYunOSS/cli.py
JYAliYun/AliYunRAM/RAMUser.py
JYAliYun/AliYunRAM/__init__.py
JYAliYun/Tools/__init__.py
JYAliYun/Tools/jy_requests.py
JYAliYun/util/__init__.py
JYAliYun/util/print_helper.py
JYAliYun/util/string_helper.py