Metadata-Version: 1.0
Name: JYAliYun
Version: 0.3.7
Summary: Aliyun Service Library
Home-page: https://github.com/meisanggou/AliYun
Author: meisanggou
Author-email: zhouheng@gene.ac
License: MIT
Keywords: JYAliYun
Platform: UNKNOWN
